LICENSE
MANIFEST.in
README.rst
REQUIREMENTS
distribute_setup.py
mailworker.py
setup.py
examples/example.py
tests/test_mail_worker.py